{
  "build": {
    "beforeDevCommand": "npm run dev",
    "beforeBuildCommand": "npm run build",
    "devPath": "http://localhost:1420",
    "distDir": "../dist"
  },
  "package": {
    "productName": "QuickNginx",
    "version": "1.0.0"
  },
  "tauri": {
    "allowlist": {
      "all": false,
      "shell": {
        "all": true,
        "execute": true,
        "sidecar": true,
        "open": true
      },
      "fs": {
        "all": true,
        "readFile": true,
        "writeFile": true,
        "readDir": true,
        "scope": ["**"]
      }
    },
    "systemTray": {
      "iconPath": "icons/icon.png",
      "iconAsTemplate": true
    },
    "bundle": {
      "active": true,
      "category": "DeveloperTool",
      "copyright": "",
      "deb": {
        "depends": []
      },
      "externalBin": [],
      "icon": [
        "icons/32x32.png",
        "icons/128x128.png",
        "icons/128x128@2x.png",
        "icons/icon.icns",
        "icons/icon.ico"
      ],
      "identifier": "com.quicknginx.dev",
      "longDescription": "Nginx 管理工具",
      "macOS": {
        "entitlements": null,
        "exceptionDomain": "",
        "frameworks": [],
        "providerShortName": null,
        "signingIdentity": null
      },
      "resources": [],
      "shortDescription": "Nginx 管理工具",
      "targets": "all",
      "windows": {
        "certificateThumbprint": null,
        "digestAlgorithm": "sha256",
        "timestampUrl": ""
      }
    },
    "security": {
      "csp": null
    },
    "updater": {
      "active": false
    },
    "windows": []
  }
} 